jshunter/__init__.py
jshunter/cli/__init__.py
jshunter/cli/jshunter.py
jshunter/cli/requirements.txt
jshunter/web/__init__.py
jshunter/web/main.py
jshunter-2.0.2.dist-info/licenses/LICENSE
jshunter-2.0.2.dist-info/METADATA
jshunter-2.0.2.dist-info/WHEEL
jshunter-2.0.2.dist-info/entry_points.txt
jshunter-2.0.2.dist-info/top_level.txt
jshunter-2.0.2.dist-info/RECORD
