Metadata-Version: 2.4
Name: jshunter
Version: 2.0.2
Summary: High-Performance JavaScript Security Scanner - Process 1M URLs in ~5 hours with Telegram & Discord bot integration
Home-page: https://github.com/iamunixtz/JsHunter
Author: iamunixtz
Author-email: iamunixtz@example.com
Project-URL: Bug Reports, https://github.com/iamunixtz/JsHunter/issues
Project-URL: Source, https://github.com/iamunixtz/JsHunter
Project-URL: Documentation, https://github.com/iamunixtz/JsHunter#readme
Keywords: security,javascript,scanner,trufflehog,secrets,api-keys,tokens,high-performance,parallel-processing
Classifier: Development Status :: 5 - Production/Stable
Classifier: Intended Audience :: Developers
Classifier: Intended Audience :: Information Technology
Classifier: Topic :: Security
Classifier: Topic :: Internet :: WWW/HTTP :: Indexing/Search
Classifier: License :: OSI Approved :: MIT License
Classifier: Programming Language :: Python :: 3
Classifier: Programming Language :: Python :: 3.8
Classifier: Programming Language :: Python :: 3.9
Classifier: Programming Language :: Python :: 3.10
Classifier: Programming Language :: Python :: 3.11
Classifier: Programming Language :: Python :: 3.12
Classifier: Programming Language :: Python :: 3.13
Classifier: Operating System :: OS Independent
Requires-Python: >=3.8
License-File: LICENSE
Requires-Dist: aiohttp>=3.8.0
Requires-Dist: aiofiles>=23.0.0
Requires-Dist: requests>=2.28.0
Dynamic: author
Dynamic: author-email
Dynamic: classifier
Dynamic: description
Dynamic: description-content-type
Dynamic: home-page
Dynamic: keywords
Dynamic: license-file
Dynamic: project-url
Dynamic: requires-dist
Dynamic: requires-python
Dynamic: summary
